MangaCrawler/MAL.py
MangaCrawler/Manga.py
MangaCrawler/MangaCrawler.py
MangaCrawler/MangaFox.py
MangaCrawler/MangaSite.py
MangaCrawler/Settings.py
MangaCrawler/XML.py
MangaCrawler/__init__.py
MangaCrawler-1.0.0a1.dist-info/DESCRIPTION.rst
MangaCrawler-1.0.0a1.dist-info/METADATA
MangaCrawler-1.0.0a1.dist-info/RECORD
MangaCrawler-1.0.0a1.dist-info/WHEEL
MangaCrawler-1.0.0a1.dist-info/entry_points.txt
MangaCrawler-1.0.0a1.dist-info/metadata.json
MangaCrawler-1.0.0a1.dist-info/top_level.txt
