Metadata-Version: 2.0
Name: MangaCrawler
Version: 1.0.0a1
Summary: Crawler for finding manga to read.
Home-page: https://github.com/SanteriHetekivi/MangaCrawler
Author: Santeri Hetekivi
Author-email: santeri@hetekivi.com
License: Apache License 2.0
Keywords: manga myanimelist crawler
Platform: UNKNOWN
Classifier: Development Status :: 3 - Alpha
Classifier: Intended Audience :: Developers
Classifier: Topic :: Software Development :: Build Tools
Classifier: License :: OSI Approved :: Apache Software License
Classifier: Programming Language :: Python :: 3.5
Classifier: Programming Language :: Python :: 3.6
Classifier: Programming Language :: Python :: 3 :: Only
Classifier: Natural Language :: English
Requires-Dist: Jinja2
Requires-Dist: beautifulsoup4
Requires-Dist: bs4
Requires-Dist: lxml
Requires-Dist: py-bing-search
Requires-Dist: unidecode
Provides-Extra: dev
Provides-Extra: test
